rd_crawler/cli.py
rd_crawler/items.py
rd_crawler/keywords.txt
rd_crawler/middlewarers.py
rd_crawler/pipelines.py
rd_crawler/settings.py
rd_crawler/spiders/bizinfo_spider.py
rd_crawler/spiders/keit_spider.py
rd_crawler/spiders/smetch_spider.py
rd_crawler-0.1.11.dist-info/METADATA
rd_crawler-0.1.11.dist-info/WHEEL
rd_crawler-0.1.11.dist-info/entry_points.txt
rd_crawler-0.1.11.dist-info/top_level.txt
rd_crawler-0.1.11.dist-info/RECORD
