Metadata-Version: 2.4
Name: rd_crawler
Version: 0.1.11
Summary: 중소기업 R&D 사업정보 수집 크롤러
Author: Dongsoo Kim
License-Expression: MIT
Project-URL: Homepage, https://github.com/yourusername/rd_crawler
Project-URL: Bug Tracker, https://github.com/yourusername/rd_crawler/issues
Classifier: Programming Language :: Python :: 3
Classifier: Operating System :: OS Independent
Requires-Python: >=3.8
Requires-Dist: scrapy>=2.11.0
Requires-Dist: pandas
Requires-Dist: openpyxl
Provides-Extra: dev
Requires-Dist: black; extra == "dev"
Requires-Dist: isort; extra == "dev"
Requires-Dist: mypy; extra == "dev"
Requires-Dist: pytest; extra == "dev"
Requires-Dist: pytest-cov; extra == "dev"
